[
  {
    "match_id": 1,
    "series_name": "FIFA World Cup 2026",
    "teams": {
      "team_1": "Mexico",
      "team_1_code": "MX",
      "team_2": "South Africa",
      "team_2_code": "ZA"
    },
    "match_type": "Group Stage",
    "date": {
      "day": "11",
      "month": "06",
      "year": "2026"
    },
    "time": "03:00 PM (Local) / 01:00 AM (BST)",
    "venue": "Estadio Azteca, Mexico City, Mexico",
    "tv_channels": ["FOX Sports", "Telemundo", "T Sports", "Toffee", "Sony Sports Network"]
  },
  {
    "match_id": 2,
    "series_name": "FIFA World Cup 2026",
    "teams": {
      "team_1": "South Korea",
      "team_1_code": "KR",
      "team_2": "Czech Republic",
      "team_2_code": "CZ"
    },
    "match_type": "Group Stage",
    "date": {
      "day": "11",
      "month": "06",
      "year": "2026"
    },
    "time": "10:00 PM (ET)",
    "venue": "Guadalajara Stadium, Guadalajara, Mexico",
    "tv_channels": ["FS1", "T Sports", "Sony Sports Network"]
  },
  {
    "match_id": 3,
    "series_name": "FIFA World Cup 2026",
    "teams": {
      "team_1": "Canada",
      "team_1_code": "CA",
      "team_2": "Bosnia and Herzegovina",
      "team_2_code": "BA"
    },
    "match_type": "Group Stage",
    "date": {
      "day": "12",
      "month": "06",
      "year": "2026"
    },
    "time": "03:00 PM (Local) / 01:00 AM (BST)",
    "venue": "BMO Field, Toronto, Canada",
    "tv_channels": ["CTV", "TSN", "FOX Sports", "T Sports"]
  },
  {
    "match_id": 4,
    "series_name": "FIFA World Cup 2026",
    "teams": {
      "team_1": "United States",
      "team_1_code": "US",
      "team_2": "Paraguay",
      "team_2_code": "PY"
    },
    "match_type": "Group Stage",
    "date": {
      "day": "12",
      "month": "06",
      "year": "2026"
    },
    "time": "09:00 PM (ET)",
    "venue": "SoFi Stadium, Los Angeles, USA",
    "tv_channels": ["FOX Sports", "Tubi", "T Sports", "Sony Sports Network"]
  },
  {
    "match_id": 5,
    "series_name": "FIFA World Cup 2026",
    "teams": {
      "team_1": "Qatar",
      "team_1_code": "QA",
      "team_2": "Switzerland",
      "team_2_code": "CH"
    },
    "match_type": "Group Stage",
    "date": {
      "day": "13",
      "month": "06",
      "year": "2026"
    },
    "time": "03:00 PM (ET)",
    "venue": "Levi's Stadium, San Francisco Bay, USA",
    "tv_channels": ["FOX Sports", "T Sports", "Sony Sports Network"]
  },
  {
    "match_id": 6,
    "series_name": "FIFA World Cup 2026",
    "teams": {
      "team_1": "Brazil",
      "team_1_code": "BR",
      "team_2": "Morocco",
      "team_2_code": "MA"
    },
    "match_type": "Group Stage",
    "date": {
      "day": "13",
      "month": "06",
      "year": "2026"
    },
    "time": "06:00 PM (ET)",
    "venue": "Gillette Stadium, Boston, USA",
    "tv_channels": ["FOX Sports", "Telemundo", "T Sports", "Sony Sports Network"]
  },
  {
    "match_id": 7,
    "series_name": "FIFA World Cup 2026",
    "teams": {
      "team_1": "Haiti",
      "team_1_code": "HT",
      "team_2": "Scotland",
      "team_2_code": "SCO"
    },
    "match_type": "Group Stage",
    "date": {
      "day": "13",
      "month": "06",
      "year": "2026"
    },
    "time": "09:00 PM (ET)",
    "venue": "Gillette Stadium, Boston, USA",
    "tv_channels": ["FOX Sports", "T Sports", "Sony Sports Network"]
  },
  {
    "match_id": 8,
    "series_name": "FIFA World Cup 2026",
    "teams": {
      "team_1": "Australia",
      "team_1_code": "AU",
      "team_2": "Turkey",
      "team_2_code": "TR"
    },
    "match_type": "Group Stage",
    "date": {
      "day": "13",
      "month": "06",
      "year": "2026"
    },
    "time": "12:00 AM (ET - June 14) / 09:00 PM (Local)",
    "venue": "BC Place, Vancouver, Canada",
    "tv_channels": ["FOX Sports", "T Sports", "Sony Sports Network"]
  },
  {
    "match_id": 9,
    "series_name": "FIFA World Cup 2026",
    "teams": {
      "team_1": "Germany",
      "team_1_code": "DE",
      "team_2": "Curaçao",
      "team_2_code": "CW"
    },
    "match_type": "Group Stage",
    "date": {
      "day": "14",
      "month": "06",
      "year": "2026"
    },
    "time": "04:00 PM (ET)",
    "venue": "Houston Stadium, Houston, USA",
    "tv_channels": ["FOX Sports", "T Sports", "Sony Sports Network"]
  },
  {
    "match_id": 10,
    "series_name": "FIFA World Cup 2026",
    "teams": {
      "team_1": "Netherlands",
      "team_1_code": "NL",
      "team_2": "Japan",
      "team_2_code": "JP"
    },
    "match_type": "Group Stage",
    "date": {
      "day": "14",
      "month": "06",
      "year": "2026"
    },
    "time": "04:00 PM (ET)",
    "venue": "Dallas Stadium, Arlington, USA",
    "tv_channels": ["FOX Sports", "T Sports", "Sony Sports Network"]
  },
  {
    "match_id": 11,
    "series_name": "FIFA World Cup 2026",
    "teams": {
      "team_1": "Spain",
      "team_1_code": "ES",
      "team_2": "Cape Verde",
      "team_2_code": "CV"
    },
    "match_type": "Group Stage",
    "date": {
      "day": "15",
      "month": "06",
      "year": "2026"
    },
    "time": "06:00 PM (ET)",
    "venue": "Atlanta Stadium, Atlanta, USA",
    "tv_channels": ["FOX Sports", "T Sports", "Sony Sports Network"]
  },
  {
    "match_id": 12,
    "series_name": "FIFA World Cup 2026",
    "teams": {
      "team_1": "Argentina",
      "team_1_code": "AR",
      "team_2": "Algeria",
      "team_2_code": "DZ"
    },
    "match_type": "Group Stage",
    "date": {
      "day": "16",
      "month": "06",
      "year": "2026"
    },
    "time": "03:00 PM (Local)",
    "venue": "Dallas Stadium, Arlington, USA",
    "tv_channels": ["FOX Sports", "T Sports", "Sony Sports Network"]
  },
  {
    "match_id": 13,
    "series_name": "FIFA World Cup 2026",
    "teams": {
      "team_1": "France",
      "team_1_code": "FR",
      "team_2": "Senegal",
      "team_2_code": "SN"
    },
    "match_type": "Group Stage",
    "date": {
      "day": "16",
      "month": "06",
      "year": "2026"
    },
    "time": "03:00 PM (ET)",
    "venue": "New York New Jersey Stadium, East Rutherford, USA",
    "tv_channels": ["FOX Sports", "T Sports", "Sony Sports Network"]
  },
  {
    "match_id": 14,
    "series_name": "FIFA World Cup 2026",
    "teams": {
      "team_1": "England",
      "team_1_code": "ENG",
      "team_2": "Croatia",
      "team_2_code": "HR"
    },
    "match_type": "Group Stage",
    "date": {
      "day": "17",
      "month": "06",
      "year": "2026"
    },
    "time": "03:00 PM (CT)",
    "venue": "Dallas Stadium, Arlington, USA",
    "tv_channels": ["FOX Sports", "ITV", "T Sports", "Sony Sports Network"]
  },
  {
    "match_id": 15,
    "series_name": "FIFA World Cup 2026",
    "teams": {
      "team_1": "Portugal",
      "team_1_code": "PT",
      "team_2": "DR Congo",
      "team_2_code": "CD"
    },
    "match_type": "Group Stage",
    "date": {
      "day": "17",
      "month": "06",
      "year": "2026"
    },
    "time": "06:00 PM (ET)",
    "venue": "San Francisco Bay Stadium, Santa Clara, USA",
    "tv_channels": ["FOX Sports", "T Sports", "Sony Sports Network"]
  }
]
